proxy6_api/__init__.py
proxy6_api/exceptions.py
proxy6_api/proxy6.py
proxy_6-1.1.dist-info/LICENSE.txt
proxy_6-1.1.dist-info/METADATA
proxy_6-1.1.dist-info/WHEEL
proxy_6-1.1.dist-info/top_level.txt
proxy_6-1.1.dist-info/RECORD
