Metadata-Version: 2.1
Name: proxy-6
Version: 1.1
Summary: Simple api for proxy6.net
Home-page: https://github.com/vbxx3/proxy6_api
Author: Valentine Bobrovsky
Author-email: vbabrouski@outlook.com
License: MIT
Platform: UNKNOWN
Classifier: Programming Language :: Python :: 3
Classifier: License :: OSI Approved :: MIT License
Classifier: Operating System :: OS Independent
Requires-Dist: setuptools
Requires-Dist: requests
